cascabel/__init__.py
cascabel/__main__.py
cascabel/main.py
cascabel/.vscode/settings.json
cascabel/classes/cascabel.py
cascabel/data/.DS_Store
cascabel/data/template/.DS_Store
cascabel/data/template/controller/manager_controller.py
cascabel/data/template/controller/simple_controller.py
cascabel/data/template/database/NAME_database.py
cascabel/data/template/model/model.py
cascabel/data/template/project/.env
cascabel/data/template/project/app_config.py
cascabel/data/template/project/config.py
cascabel/data/template/project/database_config.py
cascabel/data/template/project/execute.py
cascabel/data/template/project/model_config.py
cascabel/data/template/project/route_config.py
cascabel/data/template/project/routes.py
cascabel/data/template/project/app/controllers/error_controller.py
cascabel/data/template/project/app/controllers/home_controller.py
cascabel/data/template/project/app/models/empty_file.txt
cascabel/data/template/project/app/models/main/user_model.py
cascabel/data/template/project/app/requests/empty_file.txt
cascabel/data/template/project/app/requests/user_request.py
cascabel/data/template/project/databases/app.db
cascabel/data/template/project/databases/main.db
cascabel/data/template/project/databases/databases/empty_file.txt
cascabel/data/template/project/databases/migrations/empty_file.txt
cascabel/data/template/project/resources/app/app.py
cascabel/data/template/project/resources/database/database.py
cascabel/data/template/project/resources/routes/route.py
cascabel/data/template/project/resources/vars/vars.py
cascabel/data/template/project/static/css/bootstrap.min.css
cascabel/data/template/project/static/css/style.css
cascabel/data/template/project/static/images/bootstrap.png
cascabel/data/template/project/static/images/cascabel.png
cascabel/data/template/project/static/images/flask.png
cascabel/data/template/project/static/images/icon.png
cascabel/data/template/project/static/images/laravel.png
cascabel/data/template/project/static/images/logo.png
cascabel-1.0a2.dev1.dist-info/METADATA
cascabel-1.0a2.dev1.dist-info/WHEEL
cascabel-1.0a2.dev1.dist-info/entry_points.txt
cascabel-1.0a2.dev1.dist-info/top_level.txt
cascabel-1.0a2.dev1.dist-info/RECORD
