Metadata-Version: 2.1
Name: cascabel
Version: 1.0a2.dev1
Summary: Proyecto desarrollado con el propósito de agilizar la creación de páginas web mediante el uso del framework Flask
Author: Ignacio Aguilera Oyaneder
Author-email: <ignacio.a.o@outlook.com>
Keywords: python
Classifier: Development Status :: 1 - Planning
Classifier: Intended Audience :: Developers
Classifier: Programming Language :: Python :: 3.8
Classifier: Operating System :: Unix
Classifier: Operating System :: Microsoft :: Windows
Requires-Dist: colorama
Requires-Dist: flask
Requires-Dist: python-dotenv
Requires-Dist: Flask-WTF
Requires-Dist: flask-sqlalchemy
Requires-Dist: email-validator
